[
    {
        "name": "Программист Python(Middle)",
        "city": "Москва",
        "salary": {
            "from": 100000,
            "to": 200000
        },
        "url": "https://hh.ru/vacancy/108638168",
        "description": "Отличное понимание Telegram API. Опыт разработки на Python от 2 лет. Уверенное владение Python. Опыт работы с Linux (SSH). "
    },
    {
        "name": "Backend-разработчик / Разработчик Python",
        "city": "Санкт-Петербург",
        "salary": {
            "from": 230000,
            "to": 0
        },
        "url": "https://hh.ru/vacancy/109292967",
        "description": "Высшее образование в области математики или информатики (магистр или специалист). Уверенное владение Python (либо альтернативными языками и технологиями). "
    }
]